mule/__init__.py
mule/_retry.py
mule/py.typed
mule/stop_conditions.py
mule/_attempts/__init__.py
mule/_attempts/aio.py
mule/_attempts/dataclasses.py
mule/_attempts/protocols.py
mule/_attempts/sync.py
mule_lib-0.1.0.dist-info/METADATA
mule_lib-0.1.0.dist-info/WHEEL
mule_lib-0.1.0.dist-info/licenses/LICENSE
mule_lib-0.1.0.dist-info/RECORD
