Metadata-Version: 2.4
Name: mule-lib
Version: 0.1.0
Summary: Add a stubborn streak to your code.
License-File: LICENSE
Requires-Python: >=3.9
Requires-Dist: typing-extensions>=4.13.2
